setup.cfg
setup.py
djstopie/__init__.py
djstopie/middleware.py
djstopie/models.py
djstopie.egg-info/PKG-INFO
djstopie.egg-info/SOURCES.txt
djstopie.egg-info/dependency_links.txt
djstopie.egg-info/requires.txt
djstopie.egg-info/top_level.txt