Metadata-Version: 1.0
Name: djstopie
Version: 0.0.2
Summary: Redirect misbehaved versions of IE to an error page.
Home-page: https://github.com/yola/djstopie
Author: Yola
Author-email: engineers@yola.com
License: UNKNOWN
Platform: UNKNOWN
